sardananxsrecorder/__init__.py
sardananxsrecorder/nxsrecorder.py
sardana_nxsrecorder-3.32.0.dist-info/METADATA
sardana_nxsrecorder-3.32.0.dist-info/WHEEL
sardana_nxsrecorder-3.32.0.dist-info/top_level.txt
sardana_nxsrecorder-3.32.0.dist-info/RECORD
