Metadata-Version: 2.1
Name: sardana-nxsrecorder
Version: 3.32.0
Summary: NeXus Sardana Scan Recorder
Home-page: https://github.com/nexdatas/sardana-nxs-filerecorder/
Author: Jan Kotanski
Author-email: jankotan@gmail.com
License: GNU GENERAL PUBLIC LICENSE v3
Keywords: NeXus sardana scan recorder data
Classifier: Development Status :: 5 - Production/Stable
Classifier: Intended Audience :: Science/Research
Classifier: Topic :: Scientific/Engineering :: Physics
Classifier: Topic :: Software Development :: Libraries :: Python Modules
Classifier: License :: OSI Approved :: GNU General Public License v3 (GPLv3)
Classifier: Programming Language :: Python :: 3
Classifier: Programming Language :: Python :: 3.4
Classifier: Programming Language :: Python :: 3.5
Classifier: Programming Language :: Python :: 3.6
Classifier: Programming Language :: Python :: 3.7
Classifier: Programming Language :: Python :: 3.8
Classifier: Programming Language :: Python :: 3.9
Classifier: Programming Language :: Python :: 3.10
Classifier: Programming Language :: Python :: 3.11
Classifier: Programming Language :: Python :: 3.12
Requires-Dist: lxml
Requires-Dist: numpy (>1.6.0)
